trendup_storage/__init__.py
trendup_storage/file.py
trendup_storage/file_storage.py
trendup_storage/local_storage.py
trendup_storage/models.py
trendup_storage-0.0.4.dist-info/METADATA
trendup_storage-0.0.4.dist-info/WHEEL
trendup_storage-0.0.4.dist-info/top_level.txt
trendup_storage-0.0.4.dist-info/RECORD
