Metadata-Version: 2.1
Name: trendup-storage
Version: 0.0.4
Summary: Useful towel-related stuff.
Home-page: http://pypi.python.org/pypi/MyApplication_v010/
Author: JerryLin
Author-email: jerry.lin@keeptossinglab.com
Classifier: Programming Language :: Python :: 3
Classifier: License :: OSI Approved :: MIT License
Requires-Dist: attrs
